{
    "2025-05-10": [
        {
            "title": "KRQE Weather Academy visits Adobe Acres Elementary School",
            "description": "ALBUQUERQUE, N.M. (KRQE) – Meteorologists with KRQE News 13 continue to visit schools around the metro area as part of KRQE’s Weather Academy. KRQE...",
            "source": "KRQE News 13",
            "url": "https://www.krqe.com/weather-academy/krqe-weather-academy-visits-adobe-acres-elementary-school-2/",
            "publishedAt": "2025-05-10T00:39:38Z"
        },
        {
            "title": "Adobe Just Made Photoshop’s HSL Tool Far More Powerful",
            "description": "Adobe just rolled out a significant update to Photoshop’s Hue/Saturation (HSL) adjustment tool, and it’s something you'll want to know about. Coming to you from Blake Rudis with f64 Academy, this practical video highlights the overhaul of Photoshop's HSL adju…",
            "source": "Fstoppers",
            "url": "https://fstoppers.com/photoshop/adobe-just-made-photoshops-hsl-tool-far-more-powerful-701085",
            "publishedAt": "2025-05-10T12:03:01Z"
        },
        {
            "title": "Adobe Inc. (ADBE): Among Paul Tudor Jones’ Stock Picks with Huge Upside Potential",
            "description": "We recently published an article titled Billionaire Paul Tudor Jones’ 10 Stocks Picks with Huge Upside Potential. In this article, we are going to take a...",
            "source": "Yahoo Entertainment",
            "url": "https://finance.yahoo.com/news/adobe-inc-adbe-among-paul-123156652.html",
            "publishedAt": "2025-05-10T12:31:56Z"
        },
        {
            "title": "Photoshop’s New Actions Panel Changes A Lot",
            "description": "Adobe has updated Photoshop with an innovative new Actions Panel, making workflows faster and more intuitive. Coming to you from Unmesh Dinda with PiXimperfect, this helpful video walks through how the updated Actions Panel works, showing off its power throug…",
            "source": "Fstoppers",
            "url": "https://fstoppers.com/photoshop/photoshops-new-actions-panel-changes-lot-701186",
            "publishedAt": "2025-05-10T19:03:01Z"
        }
    ],
    "2025-05-13": [
        {
            "title": "Daily Deal: Adobe Photoshop Elements 2025 3-Year License",
            "description": "Edit with the magic of AI, create with stylish effects and templates, and be creative on the go. With Adobe Photoshop Elements, it’s never been easier to fix flaws, fine-tune specific areas, and add motion to quickly bring your vision to life. A 3-year licens…",
            "source": "Techdirt",
            "url": "https://www.techdirt.com/2025/05/13/daily-deal-adobe-photoshop-elements-2025-3-year-license-2/",
            "publishedAt": "2025-05-13T17:41:00Z"
        },
        {
            "title": "From Amazon to Adobe: is 2025 the year of the 'quiet rebrand'?",
            "description": "Jaguar, take note: splashy rebrands are so 2024.",
            "source": "Creative Bloq",
            "url": "https://www.creativebloq.com/design/branding/from-amazon-to-adobe-is-2025-the-year-of-the-quiet-rebrand",
            "publishedAt": "2025-05-13T06:00:00Z"
        },
        {
            "title": "Eddie AI Launches its First NLE Extension With Adobe Premiere Pro Plugin",
            "description": "Eddie AI\r\n, the agentic assistant video editor for professionals which we’ve covered on the site in the past, has just launched its first non-linear editor (NLE) plugin with the Eddie Helper extension for Adobe Premiere Pro. Let’s take a look at this new Prem…",
            "source": "Nofilmschool.com",
            "url": "https://nofilmschool.com/eddie-ai-premiere-pro-plugin",
            "publishedAt": "2025-05-13T14:31:12Z"
        },
        {
            "title": "Better Results: Photoshop’s New Object Removal Explained",
            "description": "Adobe recently released a new removal tool in Photoshop beta, offering a streamlined way to eliminate unwanted objects without relying on generative fill. This update simplifies editing, saves your generative credits, and delivers cleaner results. Coming to y…",
            "source": "Fstoppers",
            "url": "https://fstoppers.com/photoshop/better-results-photoshops-new-object-removal-explained-701346",
            "publishedAt": "2025-05-13T19:03:01Z"
        },
        {
            "title": "If You Invested $10K In Adobe Stock 10 Years Ago, How Much Would You Have Now?",
            "description": null,
            "source": "Yahoo Entertainment",
            "url": "https://consent.yahoo.com/v2/collectConsent?sessionId=1_cc-session_f0d484c0-c56c-4fda-be1b-17e1293e68f3",
            "publishedAt": "2025-05-13T12:01:49Z"
        },
        {
            "title": "Tool Tip Tuesday for Adobe Premiere Pro: Ooops…I imported off my Desktop/Downloads/Documents folder",
            "description": "Welcome to Tool Tip Tuesday for Adobe Premiere Pro on ProVideo Coalition It happens to everybody. You’re in a rush, and a key piece of content ends up on your desktop or your downloads folder. You import it and continue editing. Except now this piece of media…",
            "source": "Provideocoalition.com",
            "url": "https://www.provideocoalition.com/tool-tip-tuesday-stop-importing-off-your-desktop-oops/",
            "publishedAt": "2025-05-13T16:00:51Z"
        },
        {
            "title": "Lenovo Slim Pro 9: 16\" 3.2K 165Hz Mini-LED Touch, i9-13905H, RTX 4050, 32GB LPDDR5, 1TB SSD $1094.05 at eBay",
            "description": "*Lowest price ever!* \n \nSold by *Lenovo via eBay.* \n \n*SPECS:*[list][*]16\" 3.2K (3200x2000) 16:10, 165Hz, 1200-nits, 100% DCI-P3, 100% Adobe RGB, 100% sRGB, Eyesafe, DisplayHDR 1000, Dolby Vision,...",
            "source": "Slickdeals.net",
            "url": "https://slickdeals.net/f/18311458-lenovo-slim-pro-9-16-3-2k-165hz-mini-led-touch-i9-13905h-rtx-4050-32gb-lpddr5-1tb-ssd-1094-05-at-ebay?utm_source=rss&utm_content=ht&utm_medium=RSS2",
            "publishedAt": "2025-05-13T04:53:22Z"
        },
        {
            "title": "How to watch and follow Adobe Women's FA Cup final",
            "description": "Everything you need to know ahead of our third consecutive showpiece occasion at Wembley.",
            "source": "Manchester United",
            "url": "https://www.manutd.com/en/news/detail/match-preview-how-to-follow-chelsea-v-manchester-united-women-fa-cup-final-18-may-2025",
            "publishedAt": "2025-05-13T12:30:00Z"
        }
    ],
    "2025-05-16": [
        {
            "title": "What’s the best CPU for Adobe Premiere Pro? It’s complicated",
            "description": "I am not a video editor. But Alex Esteves is — in fact he edits most of the videos on PCWorld’s YouTube channel and TikTok. So he knows a thing or two about what kind of PC works best for Adobe Premiere and other video editing software. And he’s in the studio…",
            "source": "PCWorld",
            "url": "https://www.pcworld.com/article/2784446/whats-the-best-cpu-for-adobe-premiere-pro-its-complicated.html",
            "publishedAt": "2025-05-16T14:00:00Z"
        },
        {
            "title": "One new PDF editor does everything Acrobat can, except charge a subscription",
            "description": "TL;DR: Replace your Adobe Acrobat subscription with a SwiftDoo PDF Pro perpetual license on sale for $29.97 (reg. $129).\r\n\n\n\n\nSubscriptions have taken over everything, from streaming to software, including PDF editors like Adobe Acrobat, but that’s not your o…",
            "source": "PCWorld",
            "url": "https://www.pcworld.com/article/2781019/one-new-pdf-editor-does-everything-acrobat-can-except-charge-a-subscription.html",
            "publishedAt": "2025-05-16T08:00:00Z"
        },
        {
            "title": "Adobe Creative Cloud Update SHAKES UP the Creative World: Meet Creative Cloud Pro, Unlimited AI, and Third-Party Integrations!",
            "description": "Have you felt that ripple in the digital universe? Adobe just sent out a major announcement about an Adobe Creative Cloud Update, and trust me, it’s more than just a fresh coat of paint. They’re rolling out some significant changes, particularly for users in …",
            "source": "Weandthecolor.com",
            "url": "https://weandthecolor.com/adobe-creative-cloud-update-shakes-up-the-creative-world-meet-creative-cloud-pro-unlimited-ai-and-third-party-integrations/202800",
            "publishedAt": "2025-05-16T08:51:05Z"
        },
        {
            "title": "How Adobe Express is empowering content creators of all stripes",
            "description": "Whether you're a pro designer or an entrepreneur without design skills, Adobe Express can revolutionise your content creation. Designer/founder Aseil Amgheib and 'small biz babe' Angel White explai...",
            "source": "Creative Boom",
            "url": "https://www.creativeboom.com/resources/creative-freedom-unleashed-how-adobe-express-is-empowering-entrepreneurs-worldwide/",
            "publishedAt": "2025-05-16T06:45:00Z"
        }
    ],
    "2025-05-08": [
        {
            "title": "Adobe quietly rebrands, tweaking its iconic logo",
            "description": "There's a new 'A' in town.",
            "source": "Creative Bloq",
            "url": "https://www.creativebloq.com/design/branding/adobe-rebrand",
            "publishedAt": "2025-05-08T10:52:03Z"
        },
        {
            "title": "Adobe Inc. (ADBE): Among Billionaire Ray Dalio’s Bridgewater’s Stock Picks with Huge Upside Potential",
            "description": null,
            "source": "Yahoo Entertainment",
            "url": "https://consent.yahoo.com/v2/collectConsent?sessionId=1_cc-session_e3570531-21ec-4597-8ac5-dfc1e71598c6",
            "publishedAt": "2025-05-08T23:11:48Z"
        },
        {
            "title": "Adobe, GSA ink access and discount software pact",
            "description": "Agencies can now buy the company's document management software at a significantly lower price, which is similar to the General Services Administration's agreement with Google.",
            "source": "Washingtontechnology.com",
            "url": "https://washingtontechnology.com/companies/2025/05/adobe-gsa-ink-access-and-discount-software-pact/405177/",
            "publishedAt": "2025-05-08T21:47:00Z"
        },
        {
            "title": "A4 Landscape Brand Guidelines Template for Adobe InDesign",
            "description": "Achieve Stunning Brand Consistency With Your New Go-To Brand Guidelines Template Ever wondered how some brands just look perfectly put-together, no matter where you see them? Their secret often lies in a robust set of brand guidelines. Creating these from scr…",
            "source": "Weandthecolor.com",
            "url": "https://weandthecolor.com/a4-landscape-brand-guidelines-template-for-adobe-indesign/202540",
            "publishedAt": "2025-05-08T11:59:33Z"
        },
        {
            "title": "2TB Crucial T500 PCIe Gen4 NVMe M.2 Internal Gaming Solid State Drive + 1mo Adobe CC All Apps $124.99 + Free Shipping",
            "description": "*AAAwave [aaawave.com]* has *2TB Crucial T500 PCIe Gen4 NVMe M.2 Internal Gaming Solid State Drive Up to 7300MB/s, Laptop & Desktop Compatible CT2000T500SSD8 + 1mo Adobe CC All Apps* on sale for...",
            "source": "Slickdeals.net",
            "url": "https://slickdeals.net/f/18302110-2tb-crucial-t500-pcie-gen4-nvme-m-2-internal-gaming-solid-state-drive-1mo-adobe-cc-all-apps-124-99-free-shipping?utm_source=rss&utm_content=ht&utm_medium=RSS2",
            "publishedAt": "2025-05-08T16:12:52Z"
        }
    ],
    "2025-05-14": [
        {
            "title": "How and when to use the different selection tools in Adobe Photoshop",
            "description": "In this tutorial, the iDB team shares the different types of selection tools in Adobe Photoshop and how to use them effectively.",
            "source": "Idownloadblog.com",
            "url": "https://www.idownloadblog.com/2025/05/14/adobe-photoshop-selection-tools-tutorial/",
            "publishedAt": "2025-05-14T14:40:24Z"
        },
        {
            "title": "Photoshop Express is a free and fast editor for Windows and mobile",
            "description": "Adobe Photoshop Express is a simplified photo editing app built for quick fixes and social media-ready images. Available for free on Windows, iOS and Android, it offers one-touch tools for cropping, filters, retouching, and more.Read Entire Article",
            "source": "TechSpot",
            "url": "https://www.techspot.com/downloads/6405-adobe-photoshop-express.html",
            "publishedAt": "2025-05-14T15:07:00Z"
        },
        {
            "title": "Is Adobe Inc. (ADBE) the Tech Stock That Trump’s Fellow Republican Bought Amid Market Rout?",
            "description": "We recently published a list of 10 Tech Stocks That Trump’s Fellow Republican Bought Amid Market Rout. In this article, we are going to take a look at where ...",
            "source": "Yahoo Entertainment",
            "url": "https://finance.yahoo.com/news/adobe-inc-adbe-tech-stock-165650369.html",
            "publishedAt": "2025-05-14T16:56:50Z"
        }
    ],
    "2025-05-09": [
        {
            "title": "Adobe offers US Government discounted software following DOGE review",
            "description": "Adobe will give the US Government 70% discounts on certain software subscriptions, including Acrobat packages.",
            "source": "TechRadar",
            "url": "https://www.techradar.com/pro/adobe-offers-us-government-discounted-software-following-doge-review",
            "publishedAt": "2025-05-09T14:05:00Z"
        },
        {
            "title": "Case study: Adobe rebrand",
            "description": "Adobe sought help from Mother Design in rethinking and codifying its brand system.",
            "source": "Vercel.app",
            "url": "https://motherdesign.vercel.app/work/adobe",
            "publishedAt": "2025-05-09T04:00:00Z"
        },
        {
            "title": "Adobe Inc. (ADBE): Among Billionaire Bruce Kovner’s Stock Picks with Huge Upside Potential",
            "description": null,
            "source": "Yahoo Entertainment",
            "url": "https://consent.yahoo.com/v2/collectConsent?sessionId=1_cc-session_72c1859b-9a3f-4c68-b630-2f9746d19134",
            "publishedAt": "2025-05-09T15:11:00Z"
        },
        {
            "title": "Adobe Lightroom 8.3.1 Win x64",
            "description": "Adobe Lightroom 8.3.1 Win x64 Title: Adobe Lightroom 8.3.1 Win x64 Info: Look at the flags thrown up by the exe crack file before downloading and installing 25/72 AdobeGenP.exe https://www.virustotal.com/gui/file/b92860632a6ddae2532206833cc0c4a18548d469136271…",
            "source": "Cgpersia.com",
            "url": "https://cgpersia.com/2025/05/adobe-lightroom-8-3-1-win-x64-199377.html",
            "publishedAt": "2025-05-09T13:42:35Z"
        },
        {
            "title": "Adobe Inc. (ADBE): Among Billionaire Quants’ Two Sigma’s 10 Stock Picks with Huge Upside Potential",
            "description": null,
            "source": "Yahoo Entertainment",
            "url": "https://consent.yahoo.com/v2/collectConsent?sessionId=1_cc-session_c4e2f3e1-52b1-4683-ab96-4e6a771a5ea9",
            "publishedAt": "2025-05-09T21:22:20Z"
        },
        {
            "title": "Adobe Illustrator Text to Vector Graphic: Instantly Create Stunning, Editable Vectors with AI!",
            "description": "Have you ever stared at a blank artboard, wishing your brilliant ideas could just leap from your mind into fully formed vector graphics? Imagine typing a simple description – “a serene mountain landscape at sunset” or “a playful robot cat icon” – and watching…",
            "source": "Weandthecolor.com",
            "url": "https://weandthecolor.com/adobe-illustrator-text-to-vector-graphic-instantly-create-stunning-editable-vectors-with-ai/202566",
            "publishedAt": "2025-05-09T12:28:54Z"
        }
    ],
    "2025-05-12": [
        {
            "title": "Photoshop’s HSL Adjustment Gets a Major Visual Upgrade",
            "description": "Have you ever struggled with color adjustments in Photoshop? If yes, you will surely be interested in Adobe’s recent revamp of Photoshop’s HSL adjustment tool....\nThe post Photoshop’s HSL Adjustment Gets a Major Visual Upgrade appeared first on DIY Photograph…",
            "source": "DIYphotography",
            "url": "https://www.diyphotography.net/photoshops-hsl-adjustment-gets-a-major-visual-upgrade/",
            "publishedAt": "2025-05-12T08:36:59Z"
        },
        {
            "title": "Why is it so hard for crypto liquid funds to beat bitcoin this cycle?",
            "description": "Why is it so hard for crypto liquid funds to beat bitcoin this cycle?\nBitcoin dominance and a glut of altcoin supply are contributing factors\ndengali/Shutterstock and Adobe modified by Blockworks\nThis is a segment from the 0xResearch newsletter. To read full …",
            "source": "Biztoc.com",
            "url": "https://biztoc.com/x/ecc06fa2fe39674b",
            "publishedAt": "2025-05-12T17:46:30Z"
        },
        {
            "title": "Freepik launches new enterprise AI plan - but is it enough to tackle Adobe’s dominance in the field?",
            "description": "Creative design suite now offered to big businesses",
            "source": "TechRadar",
            "url": "https://www.techradar.com/pro/freepik-launches-new-enterprise-ai-plan-but-is-it-enough-to-tackle-adobes-dominance-in-the-field",
            "publishedAt": "2025-05-12T13:15:02Z"
        },
        {
            "title": "Thought Leader Q&A: Talking Agentic Learning And AI-Focused LMSs With Dr. Allen Partridge",
            "description": "Dr. Allen Partridge from Adobe discusses how human teams and AI can team up to drive efficiency in L&D and boost productivity.\nThis post was first published on eLearning Industry.",
            "source": "Elearningindustry.com",
            "url": "https://elearningindustry.com/thought-leader-qa-talking-agentic-learning-and-ai-focused-lmss-with-dr-allen-partridge",
            "publishedAt": "2025-05-12T19:00:50Z"
        }
    ],
    "2025-05-15": [
        {
            "title": "Wix takes on Canva and Adobe with new free visual design platform",
            "description": "Wixel is very, very easy to use.",
            "source": "Creative Bloq",
            "url": "https://www.creativebloq.com/design/graphic-design-software/wix-takes-on-canva-and-adobe-with-new-free-visual-design-platform",
            "publishedAt": "2025-05-15T13:00:30Z"
        },
        {
            "title": "Wix takes aim at Adobe and Canva with new online design platform",
            "description": "From website builder to visual design suite.",
            "source": "TechRadar",
            "url": "https://www.techradar.com/pro/wix-takes-aim-at-adobe-and-canva-with-new-online-design-platform",
            "publishedAt": "2025-05-15T12:59:00Z"
        },
        {
            "title": "Udemy – Adobe Certified Professional in Photoshop – Exam Guide",
            "description": "Duration 8h 15m Project Files Included MP4 Title: Udemy – Adobe Certified Professional in Photoshop – Exam Guide Info: What you’ll learn All essential exam topics covered in depth with video lessons Hands-on projects and practice exercises to reinforce your s…",
            "source": "Cgpersia.com",
            "url": "https://cgpersia.com/2025/05/udemy-adobe-certified-professional-in-photoshop-exam-guide-199422.html",
            "publishedAt": "2025-05-15T07:51:57Z"
        }
    ],
    "2025-05-11": [
        {
            "title": "Udemy – After Effects 2025: Complete Motion Graphics & VFX Course",
            "description": "Duration 33m MP4 Title: Udemy – After Effects 2025: Complete Motion Graphics & VFX Course Info: What you’ll learn Master the core tools and features of Adobe After Effects 2025 Create stunning motion graphics and professional animations from scratch Understan…",
            "source": "Cgpersia.com",
            "url": "https://cgpersia.com/2025/05/udemy-after-effects-2025-complete-motion-graphics-vfx-course-199386.html",
            "publishedAt": "2025-05-11T11:45:37Z"
        }
    ]
}